requirements.txt
commons/duration_statistics_config.py
commons/file_config.py
commons/time_tools.py
o2despy/action.py
o2despy/assets.py
o2despy/entity.py
o2despy/event.py
o2despy/hour_counter.py
o2despy/sandbox.py
o2despy-0.0.7.dist-info/License.txt
o2despy-0.0.7.dist-info/METADATA
o2despy-0.0.7.dist-info/WHEEL
o2despy-0.0.7.dist-info/top_level.txt
o2despy-0.0.7.dist-info/RECORD
